{
  "@context": "https://schema.org",
  "@type": "Event",
  "name": "IN MOTION / An Evening with Stephen Mills",
  "description": "★ Rating: 5/10 🎭 Artistic Merit – Without details on works, composers, or dancers, performance quality remains guesswork. Ballet Austin's history suggests competent execution in Mills's neoclassical style, with clean lines and synchronized lifts, but no speci…",
  "url": "https://hadrien-cornier.github.io/Culture-Calendar/events/in-motion-an-evening-with-stephen-mills-2026-02-13-1930.html",
  "image": "https://hadrien-cornier.github.io/Culture-Calendar/og/in-motion-an-evening-with-stephen-mills-2026-02-13-1930.svg",
  "startDate": "2026-02-13",
  "location": {
    "@type": "Place",
    "name": "BalletAustin",
    "address": {
      "@type": "PostalAddress",
      "addressLocality": "Austin",
      "addressRegion": "TX"
    }
  }
}
