{
  "@context": "https://schema.org",
  "@type": "Event",
  "name": "THE PYTHON HUNT",
  "description": "★ Rating: 5/10 🎭 Artistic Merit Xander Robin's The Python Hunt delivers a lean 91-minute chase through Florida swamps, where hunters track an oversized python loose from a pet trade mishap. Robin films the pursuit in stark daylight, sweat-streaked faces and m…",
  "url": "https://hadrien-cornier.github.io/Culture-Calendar/events/the-python-hunt.html",
  "image": "https://hadrien-cornier.github.io/Culture-Calendar/og/the-python-hunt.svg",
  "startDate": "2026-05-15",
  "location": {
    "@type": "Place",
    "name": "AFS",
    "address": {
      "@type": "PostalAddress",
      "addressLocality": "Austin",
      "addressRegion": "TX"
    }
  }
}
