{
  "@context": "https://schema.org",
  "@type": "Event",
  "name": "WEST INDIES: THE FUGITIVE SLAVES OF LIBERTY",
  "description": "★ Rating: 7/10 🎭 Artistic Merit Med Hondo executes a bold hybrid of documentary, musical, and theater in West Indies, staging colonial exploitation on a single ship deck with actors lip-syncing to songs amid archival footage and maps. The craft shines in its…",
  "url": "https://hadrien-cornier.github.io/Culture-Calendar/events/west-indies-the-fugitive-slaves-of-liberty.html",
  "image": "https://hadrien-cornier.github.io/Culture-Calendar/og/west-indies-the-fugitive-slaves-of-liberty.svg",
  "startDate": "2026-06-20",
  "location": {
    "@type": "Place",
    "name": "AFS",
    "address": {
      "@type": "PostalAddress",
      "addressLocality": "Austin",
      "addressRegion": "TX"
    }
  }
}
